omero_prometheus_tools/__init__.py
omero_prometheus_tools/counts.py
omero_prometheus_tools/omero-prometheus-tools.py
omero_prometheus_tools/sessions.py
omero_prometheus_tools-0.2.3.data/data/etc/prometheus-omero-counts.yml
omero_prometheus_tools-0.2.3.data/scripts/omero-prometheus-tools.py
omero_prometheus_tools-0.2.3.dist-info/METADATA
omero_prometheus_tools-0.2.3.dist-info/WHEEL
omero_prometheus_tools-0.2.3.dist-info/top_level.txt
omero_prometheus_tools-0.2.3.dist-info/RECORD
