Metadata-Version: 2.1
Name: omero-prometheus-tools
Version: 0.2.3
Summary: Tools for monitoring OMERO with Prometheus
Home-page: UNKNOWN
License: UNKNOWN
Platform: UNKNOWN
Classifier: Operating System :: OS Independent
Classifier: Programming Language :: Python
Classifier: Programming Language :: Python :: 3
Classifier: Topic :: Scientific/Engineering
Classifier: Topic :: System :: Monitoring
Requires-Python: >=3
Requires-Dist: omero-py (>=5.6.0)
Requires-Dist: prometheus-client (==0.2.*)
Requires-Dist: PyYAML
